ShoubashouJiaoNiShixianJianyiBiteBiGolangBan/README.md
ShoubashouJiaoNiShixianJianyiBiteBiGolangBan/__init__.py
ShoubashouJiaoNiShixianJianyiBiteBiGolangBan/__main__.py
ShoubashouJiaoNiShixianJianyiBiteBiGolangBan/file.epub
ShoubashouJiaoNiShixianJianyiBiteBiGolangBan/index.html
ShoubashouJiaoNiShixianJianyiBiteBiGolangBan/css/__init__.py
ShoubashouJiaoNiShixianJianyiBiteBiGolangBan/css/annotations.css
ShoubashouJiaoNiShixianJianyiBiteBiGolangBan/css/main.css
ShoubashouJiaoNiShixianJianyiBiteBiGolangBan/css/normalize.css
ShoubashouJiaoNiShixianJianyiBiteBiGolangBan/css/popup.css
ShoubashouJiaoNiShixianJianyiBiteBiGolangBan/font/__init__.py
ShoubashouJiaoNiShixianJianyiBiteBiGolangBan/font/fontello.eot
ShoubashouJiaoNiShixianJianyiBiteBiGolangBan/font/fontello.svg
ShoubashouJiaoNiShixianJianyiBiteBiGolangBan/font/fontello.ttf
ShoubashouJiaoNiShixianJianyiBiteBiGolangBan/font/fontello.woff
ShoubashouJiaoNiShixianJianyiBiteBiGolangBan/img/__init__.py
ShoubashouJiaoNiShixianJianyiBiteBiGolangBan/img/annotator-glyph-sprite.png
ShoubashouJiaoNiShixianJianyiBiteBiGolangBan/img/annotator-icon-sprite.png
ShoubashouJiaoNiShixianJianyiBiteBiGolangBan/img/apple-touch-icon.png
ShoubashouJiaoNiShixianJianyiBiteBiGolangBan/img/cancelfullscreen.png
ShoubashouJiaoNiShixianJianyiBiteBiGolangBan/img/close.png
ShoubashouJiaoNiShixianJianyiBiteBiGolangBan/img/fullscreen.png
ShoubashouJiaoNiShixianJianyiBiteBiGolangBan/img/loader.gif
ShoubashouJiaoNiShixianJianyiBiteBiGolangBan/img/menu-icon.png
ShoubashouJiaoNiShixianJianyiBiteBiGolangBan/img/save.png
ShoubashouJiaoNiShixianJianyiBiteBiGolangBan/img/saved.png
ShoubashouJiaoNiShixianJianyiBiteBiGolangBan/img/settings-s.png
ShoubashouJiaoNiShixianJianyiBiteBiGolangBan/img/settings.png
ShoubashouJiaoNiShixianJianyiBiteBiGolangBan/img/star.png
ShoubashouJiaoNiShixianJianyiBiteBiGolangBan/js/__init__.py
ShoubashouJiaoNiShixianJianyiBiteBiGolangBan/js/epub.js
ShoubashouJiaoNiShixianJianyiBiteBiGolangBan/js/epub.min.js
shoubashou_jiao_ni_shixian_jianyi_bite_bi_golang_ban-2024.3.5.0.dist-info/METADATA
shoubashou_jiao_ni_shixian_jianyi_bite_bi_golang_ban-2024.3.5.0.dist-info/WHEEL
shoubashou_jiao_ni_shixian_jianyi_bite_bi_golang_ban-2024.3.5.0.dist-info/entry_points.txt
shoubashou_jiao_ni_shixian_jianyi_bite_bi_golang_ban-2024.3.5.0.dist-info/top_level.txt
shoubashou_jiao_ni_shixian_jianyi_bite_bi_golang_ban-2024.3.5.0.dist-info/RECORD
